otto_shell/__init__.py
otto_shell/cli.py
otto_shell/commands.py
otto_shell/hci.py
otto_shell/openai.py
otto_shell/prompt.py
otto_shell/repl.py
otto_shell/state.py
otto_shell/temp.md
otto_shell/utils.py
otto_shell/flows/git.py
otto_shell-0.0.7.dist-info/METADATA
otto_shell-0.0.7.dist-info/WHEEL
otto_shell-0.0.7.dist-info/entry_points.txt
otto_shell-0.0.7.dist-info/licenses/LICENSE
otto_shell-0.0.7.dist-info/RECORD
